<?xml version="1.0" encoding="UTF-8"?>
<quiz>


<question type="category">
<category>
<text>$course$/vufgb-discretevariable-005-en-moodle/Variable type/Discrete variable, Measurement Level/Nominal, Measurement Level</text>
</category>
</question>


<question type="multichoice">
<name>
<text> Q1 : Variable-type_vufgb-discretevariable-005-en_vufgb-discretevariable-005-en </text>
</name>
<questiontext format="html">
<text><![CDATA[
<style type="text/css" rel="stylesheet">
/* tables with alternating shading */
.table_shade {
    border-collapse: collapse;
    border-spacing: 0;
    border:1px solid #FFFFFF;
    background-color: #FFFFFF;
}
.table_shade th {
    border:1px solid #FFFFFF;
    background: #D5D5D5;
}
.table_shade td {
    border:1px solid #FFFFFF;
}
.table_shade .odd {
    background: #EEEEEE;
}
.table_shade .even {
    background: #FBFBFB;
}
</style>
<p>
<p>For a survey on political preference and gender, each person in the sample is asked which political party they voted for in the last House of Representatives elections in 2013. The following properties apply to this variable:</p>
</p>]]></text>
</questiontext>
<generalfeedback format="html">
<text><![CDATA[<p>
</p>]]></text>
</generalfeedback>
<penalty>0</penalty>
<defaultgrade>1</defaultgrade>
<shuffleanswers>false</shuffleanswers>
<single>true</single>
<answernumbering>abc</answernumbering>
<answer fraction="0" format="html">
<text><![CDATA[<p>
Numeric, ordinal and continuous.
</p>]]></text>
<feedback format="html">
<text><![CDATA[<p>
Incorrect
</p>]]></text>
</feedback>
</answer>
<answer fraction="0" format="html">
<text><![CDATA[<p>
Categorical, ordinal and discrete.
</p>]]></text>
<feedback format="html">
<text><![CDATA[<p>
Incorrect
</p>]]></text>
</feedback>
</answer>
<answer fraction="0" format="html">
<text><![CDATA[<p>
Numeric, nominal and continuous.
</p>]]></text>
<feedback format="html">
<text><![CDATA[<p>
Incorrect
</p>]]></text>
</feedback>
</answer>
<answer fraction="100" format="html">
<text><![CDATA[<p>
Categorical, nominal and discrete.
</p>]]></text>
<feedback format="html">
<text><![CDATA[<p>
Correct
</p>]]></text>
</feedback>
</answer>
</question>

</quiz>
