<?xml version="1.0" encoding="UTF-8"?>
<quiz>


<question type="category">
<category>
<text>$course$/uu-homoscedasticity-008-nl-wooclap/Assumptions/Homoscedasticity</text>
</category>
</question>


<question type="multichoice">
<name>
<text> Q1 : Assumptions_uu-homoscedasticity-008-nl_uu-homoscedasticity-008-nl </text>
</name>
<questiontext format="html">
<text><![CDATA[
<style type="text/css" rel="stylesheet">
/* tables with alternating shading */
.table_shade {
    border-collapse: collapse;
    border-spacing: 0;
    border:1px solid #FFFFFF;
    background-color: #FFFFFF;
}
.table_shade th {
    border:1px solid #FFFFFF;
    background: #D5D5D5;
}
.table_shade td {
    border:1px solid #FFFFFF;
}
.table_shade .odd {
    background: #EEEEEE;
}
.table_shade .even {
    background: #FBFBFB;
}
</style>
<p>
<p>Wat is geen aanname bij multipele lineaire regressie?</p>
</p>]]></text>
</questiontext>
<generalfeedback format="html">
<text><![CDATA[<p>
<p>Homoscedasticiteit is een assumptie bij multipele lineaire regressie. Hetereoscedasticiteit dient juist voorkomen te worden.</p>
</p>]]></text>
</generalfeedback>
<penalty>0</penalty>
<defaultgrade>1</defaultgrade>
<shuffleanswers>false</shuffleanswers>
<single>true</single>
<answernumbering>abc</answernumbering>
<answer fraction="0" format="html">
<text><![CDATA[<p>
Onafhankelijke observaties
</p>]]></text>
</answer>
<answer fraction="100" format="html">
<text><![CDATA[<p>
Hetereoscedasticiteit
</p>]]></text>
</answer>
<answer fraction="0" format="html">
<text><![CDATA[<p>
Normaal verdeelde errors
</p>]]></text>
</answer>
<answer fraction="0" format="html">
<text><![CDATA[<p>
Lineaire relaties tussen de X-en en Y
</p>]]></text>
</answer>
</question>

</quiz>
