<?xml version="1.0" encoding="UTF-8"?>
<quiz>


<question type="category">
<category>
<text>$course$/uu-Power-820-nl-wooclap/Inferential Statistics/NHST/Power</text>
</category>
</question>


<question type="multichoice">
<name>
<text> Q1 : Inferential_Statistics_uu-Power-820-nl_uu-Power-820-nl </text>
</name>
<questiontext format="html">
<text><![CDATA[
<style type="text/css" rel="stylesheet">
/* tables with alternating shading */
.table_shade {
    border-collapse: collapse;
    border-spacing: 0;
    border:1px solid #FFFFFF;
    background-color: #FFFFFF;
}
.table_shade th {
    border:1px solid #FFFFFF;
    background: #D5D5D5;
}
.table_shade td {
    border:1px solid #FFFFFF;
}
.table_shade .odd {
    background: #EEEEEE;
}
.table_shade .even {
    background: #FBFBFB;
}
</style>
<p>
<p>Een docent wil weten of de huidige groep eerstejaarsstudenten beter presteert dan de eerstejaars in het afgelopen jaar. Hij doet dit door middel van het vergelijken van de gemiddelde tentamencijfers. Vorig jaar was dat gemiddelde 6.3. Uit het huidige jaar wordt nu een steekproef van 61 studenten getrokken. De docent vindt dat er sprake is van een verbetering indien tenminste een gemiddeld tentamencijfer van 6.8 wordt gehaald. De spreiding in de populatie is onveranderd, nl. <span class="math inline">\(\sigma\)</span> = 1.7.</p>
<p>Wat is de power van deze toets bij <span class="math inline">\(\alpha\)</span> = .05?</p>
</p>]]></text>
</questiontext>
<generalfeedback format="html">
<text><![CDATA[<p>
</p>]]></text>
</generalfeedback>
<penalty>0</penalty>
<defaultgrade>1</defaultgrade>
<shuffleanswers>false</shuffleanswers>
<single>true</single>
<answernumbering>abc</answernumbering>
<answer fraction="0" format="html">
<text><![CDATA[<p>
.63
</p>]]></text>
<feedback format="html">
<text><![CDATA[<p>
Dit antwoord is incorrect.
</p>]]></text>
</feedback>
</answer>
<answer fraction="100" format="html">
<text><![CDATA[<p>
.74
</p>]]></text>
<feedback format="html">
<text><![CDATA[<p>
Dit antwoord is correct.
</p>]]></text>
</feedback>
</answer>
<answer fraction="0" format="html">
<text><![CDATA[<p>
.85
</p>]]></text>
<feedback format="html">
<text><![CDATA[<p>
Dit antwoord is incorrect.
</p>]]></text>
</feedback>
</answer>
<answer fraction="0" format="html">
<text><![CDATA[<p>
.95
</p>]]></text>
<feedback format="html">
<text><![CDATA[<p>
Dit antwoord is incorrect.
</p>]]></text>
</feedback>
</answer>
</question>

</quiz>
