<?xml version="1.0" encoding="UTF-8"?>
<quiz>


<question type="category">
<category>
<text>$course$/uu-Paired-samples-800-nl-wooclap/Inferential Statistics/Parametric Techniques/t-test/Paired samples</text>
</category>
</question>


<question type="multichoice">
<name>
<text> Q1 : Inferential_Statistics_uu-Paired-samples-800-nl_uu-Paired-samples-800-nl </text>
</name>
<questiontext format="html">
<text><![CDATA[
<style type="text/css" rel="stylesheet">
/* tables with alternating shading */
.table_shade {
    border-collapse: collapse;
    border-spacing: 0;
    border:1px solid #FFFFFF;
    background-color: #FFFFFF;
}
.table_shade th {
    border:1px solid #FFFFFF;
    background: #D5D5D5;
}
.table_shade td {
    border:1px solid #FFFFFF;
}
.table_shade .odd {
    background: #EEEEEE;
}
.table_shade .even {
    background: #FBFBFB;
}
</style>
<p>
<p>Een t-toets voor afhankelijke groepen wordt gebruikt om experimentele condities te vergelijken in:</p>
</p>]]></text>
</questiontext>
<penalty>0</penalty>
<defaultgrade>1</defaultgrade>
<shuffleanswers>false</shuffleanswers>
<single>true</single>
<answernumbering>abc</answernumbering>
<answer fraction="0" format="html">
<text><![CDATA[<p>
Een single-factor, independent groups-design
</p>]]></text>
</answer>
<answer fraction="0" format="html">
<text><![CDATA[<p>
Een single-factor, nonequivalent groups-design
</p>]]></text>
</answer>
<answer fraction="100" format="html">
<text><![CDATA[<p>
Een single-factor, matched groups-design
</p>]]></text>
</answer>
<answer fraction="0" format="html">
<text><![CDATA[<p>
Zowel mogelijkheid a. als mogelijkheid c.
</p>]]></text>
</answer>
</question>

</quiz>
