<?xml version="1.0" encoding="UTF-8"?>
<quiz>


<question type="category">
<category>
<text>$course$/uva-value-872-nl-wooclap/Inferential Statistics/NHST/p-value</text>
</category>
</question>


<question type="multichoice">
<name>
<text> Q1 : Inferential_Statistics_uva-value-872-nl_uva-value-872-nl </text>
</name>
<questiontext format="html">
<text><![CDATA[
<style type="text/css" rel="stylesheet">
/* tables with alternating shading */
.table_shade {
    border-collapse: collapse;
    border-spacing: 0;
    border:1px solid #FFFFFF;
    background-color: #FFFFFF;
}
.table_shade th {
    border:1px solid #FFFFFF;
    background: #D5D5D5;
}
.table_shade td {
    border:1px solid #FFFFFF;
}
.table_shade .odd {
    background: #EEEEEE;
}
.table_shade .even {
    background: #FBFBFB;
}
</style>
<p>
<p>De variabele lengte heeft in de populatie van psychologiestudenten een
normale verdeling met gemiddelde 177.6 cm en standaardafwijking van 5.0
cm. Hoe groot is de kans om in een <em>random sample</em> van 25 studenten een
gemiddelde lengte te vinden die hoger is dan 176.6?</p>
</p>]]></text>
</questiontext>
<generalfeedback format="html">
<text><![CDATA[<p>
</p>]]></text>
</generalfeedback>
<penalty>0</penalty>
<defaultgrade>1</defaultgrade>
<shuffleanswers>false</shuffleanswers>
<single>true</single>
<answernumbering>abc</answernumbering>
<answer fraction="100" format="html">
<text><![CDATA[<p>
0.841.
</p>]]></text>
<feedback format="html">
<text><![CDATA[<p>
0.841.: Correct
</p>]]></text>
</feedback>
</answer>
<answer fraction="0" format="html">
<text><![CDATA[<p>
0.977.
</p>]]></text>
<feedback format="html">
<text><![CDATA[<p>
0.977.: Incorrect
</p>]]></text>
</feedback>
</answer>
<answer fraction="0" format="html">
<text><![CDATA[<p>
1.000.
</p>]]></text>
<feedback format="html">
<text><![CDATA[<p>
1.000.: Incorrect
</p>]]></text>
</feedback>
</answer>
</question>

</quiz>
