<?xml version="1.0" encoding="UTF-8"?>
<quiz>


<question type="category">
<category>
<text>$course$/vufsw-multiple_linear_regression-1207-en-wooclap/inferential statistics/regression/multiple linear regression</text>
</category>
</question>


<question type="multichoice">
<name>
<text> Q1 : Inferential_Statistics_vufsw-multiple_linear_regression-1207-en_vufsw-multiple_linear_regression-1207-en </text>
</name>
<questiontext format="html">
<text><![CDATA[
<style type="text/css" rel="stylesheet">
/* tables with alternating shading */
.table_shade {
    border-collapse: collapse;
    border-spacing: 0;
    border:1px solid #FFFFFF;
    background-color: #FFFFFF;
}
.table_shade th {
    border:1px solid #FFFFFF;
    background: #D5D5D5;
}
.table_shade td {
    border:1px solid #FFFFFF;
}
.table_shade .odd {
    background: #EEEEEE;
}
.table_shade .even {
    background: #FBFBFB;
}
</style>
<p>
<p>Which statement(s) is/are true?<br />
 <br />
I. The “multiple correlation” is the correlation between the observed
values of the dependent variable and the predicted scores based on the
regression.<br />
II. The “proportional reduction in error” in a multivariate regression
is the sum of all proportions explained variance in the dependent
variable by all independent variables separately.</p>
</p>]]></text>
</questiontext>
<generalfeedback format="html">
<text><![CDATA[<p>
</p>]]></text>
</generalfeedback>
<penalty>0</penalty>
<defaultgrade>1</defaultgrade>
<shuffleanswers>false</shuffleanswers>
<single>true</single>
<answernumbering>abc</answernumbering>
<answer fraction="0" format="html">
<text><![CDATA[<p>
Statement I is false and statement II is true.
</p>]]></text>
<feedback format="html">
<text><![CDATA[<p>
False
</p>]]></text>
</feedback>
</answer>
<answer fraction="100" format="html">
<text><![CDATA[<p>
Both statements I and II are true.
</p>]]></text>
<feedback format="html">
<text><![CDATA[<p>
True
</p>]]></text>
</feedback>
</answer>
<answer fraction="0" format="html">
<text><![CDATA[<p>
Both statements I and II are false.
</p>]]></text>
<feedback format="html">
<text><![CDATA[<p>
False
</p>]]></text>
</feedback>
</answer>
<answer fraction="0" format="html">
<text><![CDATA[<p>
Statement I is true and statement II is false.
</p>]]></text>
<feedback format="html">
<text><![CDATA[<p>
False
</p>]]></text>
</feedback>
</answer>
</question>

</quiz>
