<?xml version="1.0" encoding="UTF-8"?>
<quiz>


<question type="category">
<category>
<text>$course$/vufsw-mixeddesignanova-0251-en-wooclap/inferential statistics/parametric techniques/anova/mixed design anova</text>
</category>
</question>


<question type="multichoice">
<name>
<text> Q1 : Inferential_Statistics_vufsw-mixeddesignanova-0251-en_vufsw-mixeddesignanova-0251-en </text>
</name>
<questiontext format="html">
<text><![CDATA[
<style type="text/css" rel="stylesheet">
/* tables with alternating shading */
.table_shade {
    border-collapse: collapse;
    border-spacing: 0;
    border:1px solid #FFFFFF;
    background-color: #FFFFFF;
}
.table_shade th {
    border:1px solid #FFFFFF;
    background: #D5D5D5;
}
.table_shade td {
    border:1px solid #FFFFFF;
}
.table_shade .odd {
    background: #EEEEEE;
}
.table_shade .even {
    background: #FBFBFB;
}
</style>
<p>
<p>Mixed design ANOVA’s …</p>
</p>]]></text>
</questiontext>
<generalfeedback format="html">
<text><![CDATA[<p>
<p>Mixed design ANOVAs contain a mixture of between- groups and repeated
measure variables, require at least two independent variables and
combine repeated-measures and independent designs. Therefore none of the
answers is correct.</p>
<p>Language<br />
English &amp; Nederlands</p>
<p>M&amp;T Mixed design ANOVA<br />
Default value</p>
<p>M&amp;T MVA<br />
Standaardwaarde</p>
</p>]]></text>
</generalfeedback>
<penalty>0</penalty>
<defaultgrade>1</defaultgrade>
<shuffleanswers>false</shuffleanswers>
<single>false</single>
<answernumbering>abc</answernumbering>
<answer fraction="-50" format="html">
<text><![CDATA[<p>
require at least four independent variables.
</p>]]></text>
<feedback format="html">
<text><![CDATA[<p>
False
</p>]]></text>
</feedback>
</answer>
<answer fraction="50" format="html">
<text><![CDATA[<p>
cannot combine repeated-measures and independent designs.
</p>]]></text>
<feedback format="html">
<text><![CDATA[<p>
False
</p>]]></text>
</feedback>
</answer>
<answer fraction="-50" format="html">
<text><![CDATA[<p>
only include a mixture of within-group and repeated-measures variables.
</p>]]></text>
<feedback format="html">
<text><![CDATA[<p>
False
</p>]]></text>
</feedback>
</answer>
<answer fraction="50" format="html">
<text><![CDATA[<p>
None of the other answers is correct
</p>]]></text>
<feedback format="html">
<text><![CDATA[<p>
True
</p>]]></text>
</feedback>
</answer>
</question>

</quiz>
