<?xml version="1.0" encoding="UTF-8"?>
<quiz>


<question type="category">
<category>
<text>$course$/vufsw-one_sample_mean-1242-en-wooclap/inferential statistics/parametric techniques/t-test/one sample mean</text>
</category>
</question>


<question type="multichoice">
<name>
<text> Q1 : Inferential_Statistics_vufsw-one_sample_mean-1242-en_vufsw-one_sample_mean-1242-en </text>
</name>
<questiontext format="html">
<text><![CDATA[
<style type="text/css" rel="stylesheet">
/* tables with alternating shading */
.table_shade {
    border-collapse: collapse;
    border-spacing: 0;
    border:1px solid #FFFFFF;
    background-color: #FFFFFF;
}
.table_shade th {
    border:1px solid #FFFFFF;
    background: #D5D5D5;
}
.table_shade td {
    border:1px solid #FFFFFF;
}
.table_shade .odd {
    background: #EEEEEE;
}
.table_shade .even {
    background: #FBFBFB;
}
</style>
<p>
<p>Suppose a teacher wants to test whether the average number of days that
students spend a week on statistics is higher than 3 days.<br />
Which type of test would he best use?</p>
</p>]]></text>
</questiontext>
<generalfeedback format="html">
<text><![CDATA[<p>
<p>It is a one sample t test, because <strong>The </strong>One Sample t Test** is
commonly used to <strong>test </strong>the following:**</p>
<ol style="list-style-type: decimal">
<li>Statistical difference between a <strong>sample</strong> mean and a known or
hypothesized value of the mean in the population.</li>
<li>Statistical difference between the <strong>sample</strong> mean and the
<strong>sample</strong> midpoint of the <strong>test</strong> variable.</li>
</ol>
<p>The <strong>independent t-test</strong>, is an inferential statistical <strong>test</strong> that
determines whether there is a statistically significant difference
between the means in two unrelated groups.</p>
<p> <strong>Use</strong> the <strong>chi</strong>-<strong>square test</strong> for independence to determine
whether there is a significant relationship between two categorical
variables.</p>
<p>Use a simple regression
<a href="http://statisticsbyjim.com/glossary/regression-analysis/"></a>to describe
the relationships between an independent variable and a dependent
variable.</p>
<p>Levels of Difficulty<br />
Easy</p>
<p>M&amp;T Hypothesis testing: means<br />
Default value</p>
<p>M&amp;T Model selection<br />
Default value</p>
</p>]]></text>
</generalfeedback>
<penalty>0</penalty>
<defaultgrade>1</defaultgrade>
<shuffleanswers>false</shuffleanswers>
<single>true</single>
<answernumbering>abc</answernumbering>
<answer fraction="0" format="html">
<text><![CDATA[<p>
Chi-square test
</p>]]></text>
<feedback format="html">
<text><![CDATA[<p>
False
</p>]]></text>
</feedback>
</answer>
<answer fraction="0" format="html">
<text><![CDATA[<p>
Independent t-test
</p>]]></text>
<feedback format="html">
<text><![CDATA[<p>
False
</p>]]></text>
</feedback>
</answer>
<answer fraction="100" format="html">
<text><![CDATA[<p>
One-sample t-test
</p>]]></text>
<feedback format="html">
<text><![CDATA[<p>
True
</p>]]></text>
</feedback>
</answer>
<answer fraction="0" format="html">
<text><![CDATA[<p>
Simple regression
</p>]]></text>
<feedback format="html">
<text><![CDATA[<p>
False
</p>]]></text>
</feedback>
</answer>
</question>

</quiz>
