<?xml version="1.0" encoding="UTF-8"?>
<quiz>


<question type="category">
<category>
<text>$course$/vufsw-pvalue-0091-nl-wooclap/inferential statistics/nhst/p-value</text>
</category>
</question>


<question type="multichoice">
<name>
<text> Q1 : Inferential_Statistics_vufsw-pvalue-0091-nl_vufsw-pvalue-0091-nl </text>
</name>
<questiontext format="html">
<text><![CDATA[
<style type="text/css" rel="stylesheet">
/* tables with alternating shading */
.table_shade {
    border-collapse: collapse;
    border-spacing: 0;
    border:1px solid #FFFFFF;
    background-color: #FFFFFF;
}
.table_shade th {
    border:1px solid #FFFFFF;
    background: #D5D5D5;
}
.table_shade td {
    border:1px solid #FFFFFF;
}
.table_shade .odd {
    background: #EEEEEE;
}
.table_shade .even {
    background: #FBFBFB;
}
</style>
<p>
<p>Stel, de geobserveerde z-score bij een hypothesetoetsing van een
proportie is 1,78.</p>
<p>Wat is de bijbehorende geobserveerde P-waarde als de nulhypothese en
alternatieve hypothese als volgt luiden:</p>
<p>H<sub>0</sub>: <em>p</em> = 0,90</p>
<p>H<sub>a</sub>: <em>p </em>&gt; 0,90</p>
</p>]]></text>
</questiontext>
<generalfeedback format="html">
<text><![CDATA[<p>
</p>]]></text>
</generalfeedback>
<penalty>0</penalty>
<defaultgrade>1</defaultgrade>
<shuffleanswers>false</shuffleanswers>
<single>true</single>
<answernumbering>abc</answernumbering>
<answer fraction="0" format="html">
<text><![CDATA[<p>
0,9625
</p>]]></text>
<feedback format="html">
<text><![CDATA[<p>
False
</p>]]></text>
</feedback>
</answer>
<answer fraction="0" format="html">
<text><![CDATA[<p>
0,9178
</p>]]></text>
<feedback format="html">
<text><![CDATA[<p>
False
</p>]]></text>
</feedback>
</answer>
<answer fraction="0" format="html">
<text><![CDATA[<p>
0,0571
</p>]]></text>
<feedback format="html">
<text><![CDATA[<p>
False
</p>]]></text>
</feedback>
</answer>
<answer fraction="0" format="html">
<text><![CDATA[<p>
0,9429
</p>]]></text>
<feedback format="html">
<text><![CDATA[<p>
False
</p>]]></text>
</feedback>
</answer>
<answer fraction="100" format="html">
<text><![CDATA[<p>
0,0375
</p>]]></text>
<feedback format="html">
<text><![CDATA[<p>
True
</p>]]></text>
</feedback>
</answer>
<answer fraction="0" format="html">
<text><![CDATA[<p>
0,0750
</p>]]></text>
<feedback format="html">
<text><![CDATA[<p>
False
</p>]]></text>
</feedback>
</answer>
</question>

</quiz>
