<?xml version="1.0" encoding="UTF-8"?>
<quiz>


<question type="category">
<category>
<text>$course$/uu-p-value-801-en-moodle/Inferential Statistics/NHST/p-value</text>
</category>
</question>


<question type="multichoice">
<name>
<text> Q1 : Inferential_Statistics_uu-p-value-801-en_uu-p-value-801-en </text>
</name>
<questiontext format="html">
<text><![CDATA[
<style type="text/css" rel="stylesheet">
/* tables with alternating shading */
.table_shade {
    border-collapse: collapse;
    border-spacing: 0;
    border:1px solid #FFFFFF;
    background-color: #FFFFFF;
}
.table_shade th {
    border:1px solid #FFFFFF;
    background: #D5D5D5;
}
.table_shade td {
    border:1px solid #FFFFFF;
}
.table_shade .odd {
    background: #EEEEEE;
}
.table_shade .even {
    background: #FBFBFB;
}
</style>
<p>
<p>A pharmaceutical company has developed a new drug against migraine and wants to test its efficacy with a sample of migraineurs. Since the drug has some known side effects, the company wants as much certainty as possible as to whether the drug actually helps against migraine. How can the company best accomplish this?</p>
</p>]]></text>
</questiontext>
<penalty>0</penalty>
<defaultgrade>1</defaultgrade>
<shuffleanswers>false</shuffleanswers>
<single>true</single>
<answernumbering>abc</answernumbering>
<answer fraction="100" format="html">
<text><![CDATA[<p>
By the usual significance level <span class="math inline">\(\alpha\)</span> = 5% to reduce to <span class="math inline">\(\alpha\)</span> = 1%.
</p>]]></text>
</answer>
<answer fraction="0" format="html">
<text><![CDATA[<p>
Due to the usual significance level <span class="math inline">\(\alpha\)</span> = 5% to increase to <span class="math inline">\(\alpha\)</span> = 10%.
</p>]]></text>
</answer>
<answer fraction="0" format="html">
<text><![CDATA[<p>
By choosing a 99% confidence interval.
</p>]]></text>
</answer>
<answer fraction="0" format="html">
<text><![CDATA[<p>
By choosing a 90% confidence interval.
</p>]]></text>
</answer>
</question>

</quiz>
