<?xml version="1.0" encoding="UTF-8"?>
<quiz>


<question type="category">
<category>
<text>$course$/uva-conditional-probability-661-nl-wooclap/Probability/Elementary Probability/Conditional probability</text>
</category>
</question>


<question type="multichoice">
<name>
<text> Q1 : Probability_uva-conditional-probability-661-nl_uva-conditional-probability-661-nl </text>
</name>
<questiontext format="html">
<text><![CDATA[
<style type="text/css" rel="stylesheet">
/* tables with alternating shading */
.table_shade {
    border-collapse: collapse;
    border-spacing: 0;
    border:1px solid #FFFFFF;
    background-color: #FFFFFF;
}
.table_shade th {
    border:1px solid #FFFFFF;
    background: #D5D5D5;
}
.table_shade td {
    border:1px solid #FFFFFF;
}
.table_shade .odd {
    background: #EEEEEE;
}
.table_shade .even {
    background: #FBFBFB;
}
</style>
<p>
<p>Gooi twee zuivere munten onafhankelijk op. Wij noemen de volgende twee
gebeurtenissen <em>A</em> en <em>B</em>:<br />
<br />
* <em>A</em> = <em>Munt bij de eerste worp</em><br />
* <em>B</em> = <em>Beide worpen geven dezelfde uitkomst</em><br />
<br />
Wat is dan de kans P(B|A)?</p>
</p>]]></text>
</questiontext>
<generalfeedback format="html">
<text><![CDATA[<p>
</p>]]></text>
</generalfeedback>
<penalty>0</penalty>
<defaultgrade>1</defaultgrade>
<shuffleanswers>false</shuffleanswers>
<single>true</single>
<answernumbering>abc</answernumbering>
<answer fraction="0" format="html">
<text><![CDATA[<p>
P (B|A) = 0,125
</p>]]></text>
<feedback format="html">
<text><![CDATA[<p>
P (B|A) = 0,125: Incorrect
</p>]]></text>
</feedback>
</answer>
<answer fraction="0" format="html">
<text><![CDATA[<p>
P (B|A) = 0,25
</p>]]></text>
<feedback format="html">
<text><![CDATA[<p>
P (B|A) = 0,25: Incorrect
</p>]]></text>
</feedback>
</answer>
<answer fraction="100" format="html">
<text><![CDATA[<p>
P (B|A) = 0,50
</p>]]></text>
<feedback format="html">
<text><![CDATA[<p>
P (B|A) = 0,50: Correct
</p>]]></text>
</feedback>
</answer>
<answer fraction="0" format="html">
<text><![CDATA[<p>
P (B|A) = 1
</p>]]></text>
<feedback format="html">
<text><![CDATA[<p>
P (B|A) = 1: Incorrect
</p>]]></text>
</feedback>
</answer>
</question>

</quiz>
