<?xml version="1.0" encoding="UTF-8"?>
<quiz>


<question type="category">
<category>
<text>$course$/vufgb-standarddeviation-011-en-wooclap/Descriptive statistics/Summary Statistics/Measures of Spread/Standard Deviation</text>
</category>
</question>


<question type="multichoice">
<name>
<text> Q1 : Descriptive-statistics_vufgb-standarddeviation-011-en_vufgb-standarddeviation-011-en </text>
</name>
<questiontext format="html">
<text><![CDATA[
<style type="text/css" rel="stylesheet">
/* tables with alternating shading */
.table_shade {
    border-collapse: collapse;
    border-spacing: 0;
    border:1px solid #FFFFFF;
    background-color: #FFFFFF;
}
.table_shade th {
    border:1px solid #FFFFFF;
    background: #D5D5D5;
}
.table_shade td {
    border:1px solid #FFFFFF;
}
.table_shade .odd {
    background: #EEEEEE;
}
.table_shade .even {
    background: #FBFBFB;
}
</style>
<p>
<p>In a sample of childrand with ADHD, the following holds true for the variable inhibition ability: <span class="math inline">\(n_{1} = 24\)</span>, <span class="math inline">\(\overline{y}_{1} = 4.5\)</span>, <span class="math inline">\(s_{1} = 1.2\)</span> and <span class="math inline">\(SS_{1} = 33.12\)</span> and in eand steekproef van kinderand met Autisme geldt voor dezelfde variabele: <span class="math inline">\(n_{2} = 26\)</span>, <span class="math inline">\(\overline{y}_{2} = 6.5\)</span>, <span class="math inline">\(s_{2} = 0.9\)</span> and <span class="math inline">\(SS_{2} = 20.25\)</span>. Bepaal de ‘pooled’ standaardafwijking over de twee groepand.</p>
</p>]]></text>
</questiontext>
<generalfeedback format="html">
<text><![CDATA[<p>
</p>]]></text>
</generalfeedback>
<penalty>0</penalty>
<defaultgrade>1</defaultgrade>
<shuffleanswers>false</shuffleanswers>
<single>true</single>
<answernumbering>abc</answernumbering>
<answer fraction="0" format="html">
<text><![CDATA[<p>
1.05
</p>]]></text>
<feedback format="html">
<text><![CDATA[<p>
Incorrect
</p>]]></text>
</feedback>
</answer>
<answer fraction="100" format="html">
<text><![CDATA[<p>
1.11
</p>]]></text>
<feedback format="html">
<text><![CDATA[<p>
Correct
</p>]]></text>
</feedback>
</answer>
<answer fraction="0" format="html">
<text><![CDATA[<p>
1.02
</p>]]></text>
<feedback format="html">
<text><![CDATA[<p>
Incorrect
</p>]]></text>
</feedback>
</answer>
<answer fraction="0" format="html">
<text><![CDATA[<p>
1.08
</p>]]></text>
<feedback format="html">
<text><![CDATA[<p>
Incorrect
</p>]]></text>
</feedback>
</answer>
</question>

</quiz>
