<?xml version="1.0" encoding="UTF-8"?>
<quiz>


<question type="category">
<category>
<text>$course$/vufsw-z-score-1097-en-wooclap/descriptive statistics/score interpretation/z-score</text>
</category>
</question>


<question type="multichoice">
<name>
<text> Q1 : Descriptive-statistics_vufsw-z-score-1097-en_vufsw-z-score-1097-en </text>
</name>
<questiontext format="html">
<text><![CDATA[
<style type="text/css" rel="stylesheet">
/* tables with alternating shading */
.table_shade {
    border-collapse: collapse;
    border-spacing: 0;
    border:1px solid #FFFFFF;
    background-color: #FFFFFF;
}
.table_shade th {
    border:1px solid #FFFFFF;
    background: #D5D5D5;
}
.table_shade td {
    border:1px solid #FFFFFF;
}
.table_shade .odd {
    background: #EEEEEE;
}
.table_shade .even {
    background: #FBFBFB;
}
</style>
<p>
<p>A recently-graduated economist gets two job offers.</p>
<p>He can get a job in the US with a monthly salary of $5.000. The mean
salary in the US equals $3.300 and the standard deviation is $800. He
can also get a job in Germany with a monthly salary of €4.000. In
Germany, the mean salary amounts to €2.800 and the standard deviation to
€500.</p>
<p>In which country can he get the highest salary (compared to the mean
salary in the country)? And how can you conclude this?</p>
</p>]]></text>
</questiontext>
<generalfeedback format="html">
<text><![CDATA[<p>
</p>]]></text>
</generalfeedback>
<penalty>0</penalty>
<defaultgrade>1</defaultgrade>
<shuffleanswers>false</shuffleanswers>
<single>true</single>
<answernumbering>abc</answernumbering>
<answer fraction="0" format="html">
<text><![CDATA[<p>
In the US, because the standard error of the offered salary is higher in the US than in Germany
</p>]]></text>
<feedback format="html">
<text><![CDATA[<p>
False
</p>]]></text>
</feedback>
</answer>
<answer fraction="100" format="html">
<text><![CDATA[<p>
In Germany, because the z-score of the offered salary is higher in Germany than in the US.
</p>]]></text>
<feedback format="html">
<text><![CDATA[<p>
True
</p>]]></text>
</feedback>
</answer>
<answer fraction="0" format="html">
<text><![CDATA[<p>
In Germany, because the standar error of the offered salary is higher in Germany than in the US
</p>]]></text>
<feedback format="html">
<text><![CDATA[<p>
False
</p>]]></text>
</feedback>
</answer>
<answer fraction="0" format="html">
<text><![CDATA[<p>
In Germany, because the correlation coefficient of the offered salary is higher in Germany than in the US
</p>]]></text>
<feedback format="html">
<text><![CDATA[<p>
False
</p>]]></text>
</feedback>
</answer>
<answer fraction="0" format="html">
<text><![CDATA[<p>
In the US, because the correlation coeffecient of the offered salary is higher in the US than in Germany
</p>]]></text>
<feedback format="html">
<text><![CDATA[<p>
False
</p>]]></text>
</feedback>
</answer>
<answer fraction="0" format="html">
<text><![CDATA[<p>
In the US, because the z-score of the offered salary is higher in the US than in Germany
</p>]]></text>
<feedback format="html">
<text><![CDATA[<p>
False
</p>]]></text>
</feedback>
</answer>
</question>

</quiz>
