<?xml version="1.0" encoding="UTF-8"?>
<quiz>


<question type="category">
<category>
<text>$course$/uu-assumptions-005-en-moodle/Assumptions</text>
</category>
</question>


<question type="multichoice">
<name>
<text> Q1 : Assumptions_uu-assumptions-005-en_uu-assumptions-005-en </text>
</name>
<questiontext format="html">
<text><![CDATA[
<style type="text/css" rel="stylesheet">
/* tables with alternating shading */
.table_shade {
    border-collapse: collapse;
    border-spacing: 0;
    border:1px solid #FFFFFF;
    background-color: #FFFFFF;
}
.table_shade th {
    border:1px solid #FFFFFF;
    background: #D5D5D5;
}
.table_shade td {
    border:1px solid #FFFFFF;
}
.table_shade .odd {
    background: #EEEEEE;
}
.table_shade .even {
    background: #FBFBFB;
}
</style>
<p>
<p>TRUE should you look at in a multiple regression analysis, to check for outliers in XY space?</p>
</p>]]></text>
</questiontext>
<penalty>0</penalty>
<defaultgrade>1</defaultgrade>
<shuffleanswers>false</shuffleanswers>
<single>true</single>
<answernumbering>abc</answernumbering>
<answer fraction="0" format="html">
<text><![CDATA[<p>
The Mahalanobis distance
</p>]]></text>
</answer>
<answer fraction="100" format="html">
<text><![CDATA[<p>
Cook’s distance
</p>]]></text>
</answer>
<answer fraction="0" format="html">
<text><![CDATA[<p>
To the normality of the distribution of the dependent variable
</p>]]></text>
</answer>
<answer fraction="0" format="html">
<text><![CDATA[<p>
None of the above answers is correct
</p>]]></text>
</answer>
</question>

</quiz>
