<?xml version="1.0" encoding="UTF-8"?>
<quiz>


<question type="category">
<category>
<text>$course$/uva-measures-of-location-182-en-moodle/Descriptive statistics/Summary Statistics/Measures of Location</text>
</category>
</question>


<question type="multichoice">
<name>
<text> Q1 : Descriptive-statistics_uva-measures-of-location-182-en_uva-measures-of-location-182-en </text>
</name>
<questiontext format="html">
<text><![CDATA[
<style type="text/css" rel="stylesheet">
/* tables with alternating shading */
.table_shade {
    border-collapse: collapse;
    border-spacing: 0;
    border:1px solid #FFFFFF;
    background-color: #FFFFFF;
}
.table_shade th {
    border:1px solid #FFFFFF;
    background: #D5D5D5;
}
.table_shade td {
    border:1px solid #FFFFFF;
}
.table_shade .odd {
    background: #EEEEEE;
}
.table_shade .even {
    background: #FBFBFB;
}
</style>
<p>
<p>Suppose a researcher has four averages over which she wants to run a <em>multiple comparison</em> confidence interval. There are six possible differences between averages and thus six confidence intervals. Now, for these six confidence intervals that</p>
</p>]]></text>
</questiontext>
<generalfeedback format="html">
<text><![CDATA[<p>
</p>]]></text>
</generalfeedback>
<penalty>0</penalty>
<defaultgrade>1</defaultgrade>
<shuffleanswers>false</shuffleanswers>
<single>true</single>
<answernumbering>abc</answernumbering>
<answer fraction="0" format="html">
<text><![CDATA[<p>
The probability is (0.95)6 that the true differences are within the limits found.
</p>]]></text>
<feedback format="html">
<text><![CDATA[<p>
The probability (0.95)6 is that the true differences are within the limits found…: Incorrect
</p>]]></text>
</feedback>
</answer>
<answer fraction="100" format="html">
<text><![CDATA[<p>
The probability is about 0.95 that the true differences are within the limits found.
</p>]]></text>
<feedback format="html">
<text><![CDATA[<p>
The probability is about 0.95 that the true differences are within the limits found…: Correct
</p>]]></text>
</feedback>
</answer>
<answer fraction="0" format="html">
<text><![CDATA[<p>
For each interval separately, the probability is 0.95 that the true difference is within the limits found.
</p>]]></text>
<feedback format="html">
<text><![CDATA[<p>
For each interval separately, the probability is 0.95 that the true difference is within the limits found…: Incorrect
</p>]]></text>
</feedback>
</answer>
</question>

</quiz>
