<?xml version="1.0" encoding="UTF-8"?>
<quiz>


<question type="category">
<category>
<text>$course$/vufsw-correlation-1099-en-moodle/descriptive statistics/summary statistics/bivariate statistics/correlation</text>
</category>
</question>


<question type="multichoice">
<name>
<text> Q1 : Descriptive-statistics_vufsw-correlation-1099-en_vufsw-correlation-1099-en </text>
</name>
<questiontext format="html">
<text><![CDATA[
<style type="text/css" rel="stylesheet">
/* tables with alternating shading */
.table_shade {
    border-collapse: collapse;
    border-spacing: 0;
    border:1px solid #FFFFFF;
    background-color: #FFFFFF;
}
.table_shade th {
    border:1px solid #FFFFFF;
    background: #D5D5D5;
}
.table_shade td {
    border:1px solid #FFFFFF;
}
.table_shade .odd {
    background: #EEEEEE;
}
.table_shade .even {
    background: #FBFBFB;
}
</style>
<p>
<p>What happens to the <strong>correlation </strong>between two variables X and Y if we
standardize them (in other words: if we transform them to their
z-scores)?</p>
<p>The correlation coefficient …</p>
</p>]]></text>
</questiontext>
<generalfeedback format="html">
<text><![CDATA[<p>
</p>]]></text>
</generalfeedback>
<penalty>0</penalty>
<defaultgrade>1</defaultgrade>
<shuffleanswers>false</shuffleanswers>
<single>true</single>
<answernumbering>abc</answernumbering>
<answer fraction="0" format="html">
<text><![CDATA[<p>
becomes 1.00.
</p>]]></text>
<feedback format="html">
<text><![CDATA[<p>
False
</p>]]></text>
</feedback>
</answer>
<answer fraction="0" format="html">
<text><![CDATA[<p>
becomes 0.00.
</p>]]></text>
<feedback format="html">
<text><![CDATA[<p>
False
</p>]]></text>
</feedback>
</answer>
<answer fraction="100" format="html">
<text><![CDATA[<p>
remains exactly the same.
</p>]]></text>
<feedback format="html">
<text><![CDATA[<p>
True
</p>]]></text>
</feedback>
</answer>
<answer fraction="0" format="html">
<text><![CDATA[<p>
can become either lower or higher depending on whether the association between X and Y is negative or positive.
</p>]]></text>
<feedback format="html">
<text><![CDATA[<p>
False
</p>]]></text>
</feedback>
</answer>
<answer fraction="0" format="html">
<text><![CDATA[<p>
can become either lower or higher depending on whether the difference between the means of X and Y is smaller or larger than 0.00.
</p>]]></text>
<feedback format="html">
<text><![CDATA[<p>
False
</p>]]></text>
</feedback>
</answer>
</question>

</quiz>
