<?xml version="1.0" encoding="UTF-8"?>
<quiz>


<question type="category">
<category>
<text>$course$/vufgb-discretevariable-006-en-wooclap/Variable type/Discrete variable, Measurement Level, Measurement Level/Interval, Measurement Level/Ratio</text>
</category>
</question>


<question type="multichoice">
<name>
<text> Q1 : Variable-type_vufgb-discretevariable-006-en_vufgb-discretevariable-006-en </text>
</name>
<questiontext format="html">
<text><![CDATA[
<style type="text/css" rel="stylesheet">
/* tables with alternating shading */
.table_shade {
    border-collapse: collapse;
    border-spacing: 0;
    border:1px solid #FFFFFF;
    background-color: #FFFFFF;
}
.table_shade th {
    border:1px solid #FFFFFF;
    background: #D5D5D5;
}
.table_shade td {
    border:1px solid #FFFFFF;
}
.table_shade .odd {
    background: #EEEEEE;
}
.table_shade .even {
    background: #FBFBFB;
}
</style>
<p>
<p>For an income and gender survey, each person in the sample is asked what their annual income, rounded in thousands of euros was in 2015. The following properties apply to this variable:</p>
</p>]]></text>
</questiontext>
<generalfeedback format="html">
<text><![CDATA[<p>
</p>]]></text>
</generalfeedback>
<penalty>0</penalty>
<defaultgrade>1</defaultgrade>
<shuffleanswers>false</shuffleanswers>
<single>true</single>
<answernumbering>abc</answernumbering>
<answer fraction="0" format="html">
<text><![CDATA[<p>
Numeric, ordinal and discrete.
</p>]]></text>
<feedback format="html">
<text><![CDATA[<p>
Incorrect
</p>]]></text>
</feedback>
</answer>
<answer fraction="0" format="html">
<text><![CDATA[<p>
Categorical, ordinal and continuous.
</p>]]></text>
<feedback format="html">
<text><![CDATA[<p>
Incorrect
</p>]]></text>
</feedback>
</answer>
<answer fraction="100" format="html">
<text><![CDATA[<p>
Numeric, interval/ratio and discrete.
</p>]]></text>
<feedback format="html">
<text><![CDATA[<p>
Correct
</p>]]></text>
</feedback>
</answer>
<answer fraction="0" format="html">
<text><![CDATA[<p>
Categorical, interval/ratio and continuous.
</p>]]></text>
<feedback format="html">
<text><![CDATA[<p>
Incorrect
</p>]]></text>
</feedback>
</answer>
</question>

</quiz>
