<?xml version="1.0" encoding="UTF-8"?>
<quiz>


<question type="category">
<category>
<text>$course$/eur-distributions-202-nl-wooclap/Distributions/Continuous/Normal</text>
</category>
</question>


<question type="multichoice">
<name>
<text> Q1 : Distributions_eur-distributions-202-nl_eur-distributions-202-nl </text>
</name>
<questiontext format="html">
<text><![CDATA[
<style type="text/css" rel="stylesheet">
/* tables with alternating shading */
.table_shade {
    border-collapse: collapse;
    border-spacing: 0;
    border:1px solid #FFFFFF;
    background-color: #FFFFFF;
}
.table_shade th {
    border:1px solid #FFFFFF;
    background: #D5D5D5;
}
.table_shade td {
    border:1px solid #FFFFFF;
}
.table_shade .odd {
    background: #EEEEEE;
}
.table_shade .even {
    background: #FBFBFB;
}
</style>
<p>
<p>Beoordeel onderstaande stellingen over transformatie van scores:</p>
<ol style="list-style-type: decimal">
<li><p>Wanneer je ruwe scores standaardiseert, zijn deze daarna bij benadering normaal verdeeld.</p></li>
<li><p>Wanneer je ruwe scores normaliseert, voer je een niet-lineaire transformatie uit.</p></li>
</ol>
</p>]]></text>
</questiontext>
<generalfeedback format="html">
<text><![CDATA[<p>
<p>Statement 1 is false: after standardization, the scores have the same distribution as the raw scores, which is not necessarily normal.</p>
<p>Statement 2 is correct: when scores are normalized, you have to perform a non-linear transformation in order to change the distribution of the raw scores (make them more normally distributed).</p>
</p>]]></text>
</generalfeedback>
<penalty>0</penalty>
<defaultgrade>1</defaultgrade>
<shuffleanswers>false</shuffleanswers>
<single>true</single>
<answernumbering>abc</answernumbering>
<answer fraction="0" format="html">
<text><![CDATA[<p>
Stelling 1 en stelling 2 zijn beiden waar
</p>]]></text>
<feedback format="html">
<text><![CDATA[<p>
Fout
</p>]]></text>
</feedback>
</answer>
<answer fraction="0" format="html">
<text><![CDATA[<p>
Stelling 1 is waar en stelling 2 is niet waar
</p>]]></text>
<feedback format="html">
<text><![CDATA[<p>
Fout
</p>]]></text>
</feedback>
</answer>
<answer fraction="100" format="html">
<text><![CDATA[<p>
Stelling 1 is niet waar en stelling 2 is waar
</p>]]></text>
<feedback format="html">
<text><![CDATA[<p>
Goed
</p>]]></text>
</feedback>
</answer>
<answer fraction="0" format="html">
<text><![CDATA[<p>
Stelling 1 en stelling 2 zijn beiden niet waar
</p>]]></text>
<feedback format="html">
<text><![CDATA[<p>
Fout
</p>]]></text>
</feedback>
</answer>
</question>

</quiz>
